pystoxx/__init__.py
pystoxx-0.1.2.dist-info/LICENSE
pystoxx-0.1.2.dist-info/METADATA
pystoxx-0.1.2.dist-info/WHEEL
pystoxx-0.1.2.dist-info/top_level.txt
pystoxx-0.1.2.dist-info/RECORD
