Metadata-Version: 2.1
Name: pystoxx
Version: 0.1.2
Summary: Search and retrieve current data and historical information for publicly traded companies
Home-page: https://github.com/recursivllc/pystoxx
Author: Saleh Alkhalifa
Author-email: alkhalifas@recursiv.tech
Keywords: stock,prices,sentiment,historical,news,dataset,api
Classifier: Programming Language :: Python :: 3
Classifier: License :: OSI Approved :: MIT License
Classifier: Operating System :: OS Independent
Requires-Python: >3.6
License-File: LICENSE
Requires-Dist: requests
